{
  "menus": {
    "main_menu": {
      "title": "Main Menu",
      "titleRGB": [8, 165, 225],
      "titlesize": 75,
      "buttons": [
        { "text": "Start Game", "code": 3 },
        { "text": "Demo", "code": 4 },
        { "text": "High Scores", "code": 5 },
        { "text": "Exit Game", "code": -10 }
      ]
    },
    "ages_menu": {
      "title": "Choose your Agent",
      "titleRGB": [8, 165, 225],
      "titlesize": 75,
      "buttons": [
        { "text": "BEELINE", "code": "0" },
        { "text": "RANDOM", "code": "1" },
        { "text": "SARSA", "code": "2" },
        { "text": "Q-LEARNING", "code": "3" },
        { "text": "EXP SARSA", "code": "4" },
        { "text": "DQ-LEARNING", "code": "5" }
      ]
    }
  },
  "logger": {
    "dictkeys": ["id", "agent", "time", "score"],
    "logfile": "visitorlog.csv"
  },
  "game": {
    "gametime": 180000,
    "n_aircraft": 30,
    "n_destinations": 7,
    "n_obstacles": 5,
    "framerate": 60,
    "fullscreen": true,
    "n_highscores": 30
  },
  "scoring": {
    "reach_dest": 200,
    "obs_collide": -20,
    "ac_collide": -500
  },
  "codes": {
    "user_end": 1,
    "time_up": 2,
    "start": 3,
    "demo": 4,
    "ac_collide": 5,
    "high_score": 5,
    "kill": -10
  },
  "aircraft": {
    "max_waypoints": 6,
    "speed_min": 100,
    "speed_max": 1000,
    "speed_default": 1000,
    "speed_scalefactor": 2000.0,
    "collision_radius": 30,
    "draw_radius": false
  }
}
